tisu/__init__.py
tisu/cli.py
tisu/models.py
tisu/parser.py
tisu/managers/__init__.py
tisu/managers/github.py
tisu/managers/jira.py
tisu-3.1.dist-info/entry_points.txt
tisu-3.1.dist-info/licenses/LICENSE
tisu-3.1.dist-info/WHEEL
tisu-3.1.dist-info/METADATA
tisu-3.1.dist-info/RECORD
