Metadata-Version: 2.4
Name: tisu
Version: 3.1
Summary: Your project's issue tracker, in a text file
Keywords: github,issues,tracking,bugs,markdown
Author-email: Martín Gaitán <gaitan@gmail.com>
Requires-Python: >=3.8
Classifier: Development Status :: 4 - Beta
Classifier: Environment :: Console
Classifier: Intended Audience :: Developers
Classifier: License :: OSI Approved :: BSD License
Classifier: Operating System :: OS Independent
Classifier: Programming Language :: Python
License-File: LICENSE
Requires-Dist: pygithub >= 1.55
Requires-Dist: docopt-ng >= 0.8.1
Requires-Dist: recommonmark
Requires-Dist: pytest ; extra == "dev"
Requires-Dist: black ; extra == "dev"
Requires-Dist: flit ; extra == "dev"
Requires-Dist: jira>=3.8.0 ; extra == "jira"
Requires-Dist: pyyaml>=6.0.2 ; extra == "jira"
Project-URL: Home, https://github.com/mgaitan/tisu
Provides-Extra: dev
Provides-Extra: jira
